spacehunter/__init__.py
spacehunter/__main__.py
spacehunter/_version.py
spacehunter/app.py
spacehunter/armoury.py
spacehunter/automaton.py
spacehunter/colors.py
spacehunter/communications.py
spacehunter/controllers.py
spacehunter/enemy.py
spacehunter/explosion.py
spacehunter/globals.py
spacehunter/helpers.py
spacehunter/levels.py
spacehunter/player.py
spacehunter/radar.py
spacehunter/spacejunk.py
spacehunter/supplyship.py
spacehunter/weapon.py
spacehunter/weapons.py
spacehunter/fonts/Roboto-Medium.ttf
spacehunter/fonts/Roboto-MediumItalic.ttf
spacehunter/images/asteroids/asteroid_1.png
spacehunter/images/asteroids/asteroid_10.png
spacehunter/images/asteroids/asteroid_2.png
spacehunter/images/asteroids/asteroid_21.png
spacehunter/images/asteroids/asteroid_22.png
spacehunter/images/asteroids/asteroid_23.png
spacehunter/images/asteroids/asteroid_24.png
spacehunter/images/asteroids/asteroid_25.png
spacehunter/images/asteroids/asteroid_26.png
spacehunter/images/asteroids/asteroid_27.png
spacehunter/images/asteroids/asteroid_28.png
spacehunter/images/asteroids/asteroid_29.png
spacehunter/images/asteroids/asteroid_3.png
spacehunter/images/asteroids/asteroid_30.png
spacehunter/images/asteroids/asteroid_4.png
spacehunter/images/asteroids/asteroid_5.png
spacehunter/images/asteroids/asteroid_6.png
spacehunter/images/asteroids/asteroid_7.png
spacehunter/images/asteroids/asteroid_8.png
spacehunter/images/asteroids/asteroid_9.png
spacehunter/images/asteroids/debris_1.png
spacehunter/images/asteroids/debris_2.png
spacehunter/images/backgrounds/deepfield.jpg
spacehunter/images/backgrounds/deepfield.png
spacehunter/images/backgrounds/starfield.png
spacehunter/images/backgrounds/starfield1jpg.jpg
spacehunter/images/backgrounds/starfield2.jpeg
spacehunter/images/backgrounds/starfield3.jpg
spacehunter/images/backgrounds/starfield4.jpg
spacehunter/images/enemies/enemyBlue1.png
spacehunter/images/enemies/wreckage_1.png
spacehunter/images/enemies/wreckage_2.png
spacehunter-0.2.0.dist-info/licenses/LICENSE
spacehunter-0.2.0.dist-info/METADATA
spacehunter-0.2.0.dist-info/WHEEL
spacehunter-0.2.0.dist-info/entry_points.txt
spacehunter-0.2.0.dist-info/top_level.txt
spacehunter-0.2.0.dist-info/RECORD
