Metadata-Version: 2.4
Name: SpaceHunter
Version: 0.2.0
Summary: SpaceHunter 2D arcade game for pygame
Author-email: semuadmin <semuadmin@semuconsulting.com>
Maintainer-email: semuadmin <semuadmin@semuconsulting.com>
License: BSD 2-Clause License
Project-URL: homepage, https://github.com/semuadmin/spacehunter
Project-URL: documentation, https://www.semuconsulting.com/spacehunter/
Project-URL: repository, https://github.com/semuadmin/spacehunter
Project-URL: changelog, https://github.com/semuadmin/spacehunter/blob/master/RELEASE_NOTES.md
Classifier: Operating System :: OS Independent
Classifier: Development Status :: 3 - Alpha
Classifier: Environment :: MacOS X
Classifier: Environment :: Win32 (MS Windows)
Classifier: Environment :: X11 Applications
Classifier: Intended Audience :: End Users/Desktop
Classifier: Programming Language :: Python :: 3
Classifier: Programming Language :: Python :: 3.9
Classifier: Programming Language :: Python :: 3.10
Classifier: Programming Language :: Python :: 3.11
Classifier: Programming Language :: Python :: 3.12
Classifier: Programming Language :: Python :: 3.13
Classifier: License :: OSI Approved :: BSD License
Classifier: Topic :: Games/Entertainment :: Arcade
Requires-Python: >=3.9
License-File: LICENSE
Requires-Dist: pygame>=2.5
Provides-Extra: deploy
Requires-Dist: build; extra == "deploy"
Requires-Dist: pip; extra == "deploy"
Requires-Dist: setuptools>=75.0; extra == "deploy"
Requires-Dist: wheel; extra == "deploy"
Provides-Extra: test
Requires-Dist: black; extra == "test"
Requires-Dist: isort; extra == "test"
Requires-Dist: pylint; extra == "test"
Dynamic: license-file
